Workbook

Sheet Assumptions
A1: Business Case — Smart Farm Asset Inspector
A3: Assumption | B3: Value | C3: Unit | D3: Source / basis
A4: DEVELOPMENT
A5: Development effort | B5: 65 | C5: person-days | D5: Estimated from this challenge: ~15 pd to reach the demonstrated state, scaled for productionisation (error handling, multi-site config, docs).
A6: Blended day rate | B6: 480 | C6: €/day | D6: Assumption — replace with the internal engineering rate.
A7: Commissioning effort per site | B7: 3 | C7: person-days | D7: Measured: field map ~0.5 pd, SLAM map ~0.5 pd, detector calibration ~0.5 pd, plus travel and handover.
A8: Annual maintenance | B8: 0.18 | C8: % of dev cost | D8: Assumption — typical software maintenance band 15-20%.
A10: HARDWARE
A11: Unitree Go2 EDU + sensors | B11: 14000 | C11: €/unit | D11: Assumption — verify against a current quotation. Includes RealSense and lidar.
A12: Hardware life | B12: 4 | C12: years | D12: Assumption.
A13: Hardware maintenance | B13: 0.1 | C13: % of capex/yr | D13: Assumption.
A15: LLM COST — priced at API rates
A16: Input tokens per mission | B16: 2100 | C16: tokens | D16: Measured: prompt is ~6,300 characters.
A17: Output tokens per mission | B17: 380 | C17: tokens | D17: Measured from live parse trials.
A18: Input price | B18: 3 | C18: €/M tokens | D18: Assumption — check current Claude Sonnet pricing.
A19: Output price | B19: 15 | C19: €/M tokens | D19: Assumption — check current Claude Sonnet pricing.
A20: Missions per robot per day | B20: 4 | C20: missions | D20: Assumption — 4 fields, one inspection each.
A21: Operating days per year | B21: 220 | C21: days | D21: Assumption — growing season, weather-limited.
A23: REVENUE
A24: Subscription per site | B24: 9600 | C24: €/year | D24: Assumption — 800 €/month. Positioned below the cost of a weekly agronomy visit.
A25: Hardware margin | B25: 0.22 | C25: % on resale | D25: Assumption.
A26: Commissioning fee per site | B26: 2400 | C26: € one-off | D26: Assumption — 3 pd at a service rate.
A28: VOLUME
A29: Sites — year 1 | B29: 3 | C29: sites | D29: Assumption — pilot customers.
A30: Sites — year 2 | B30: 10 | C30: sites | D30: Assumption.
A31: Sites — year 3 | B31: 22 | C31: sites | D31: Assumption.
A32: Robots per site | B32: 1 | C32: robots | D32: Assumption — one robot serves 20-200 ha.
A33: Annual churn | B33: 0.1 | C33: % | D33: Assumption.
A35: Every figure marked 'Assumption' is a placeholder that has not been validated with a customer or a supplier quotation. Figures marked 'Measured' come from the trials in KPI_Report.xlsx. The distinction is deliberate.

Sheet Per-mission cost
A1: LLM cost per mission
A2: Priced at API rates even though the demonstrator runs on a Claude subscription. The OAuth token is licensed for individual use; a production deployment would use an API key.
A4: Item | B4: Formula basis | C4: Value
A5: Input tokens | B5: measured | C5: =Assumptions!$B$16 -> 2100
A6: Output tokens | B6: measured | C6: =Assumptions!$B$17 -> 380
A7: Input cost | B7: tokens / 1e6 x price | C7: =C5/1000000*Assumptions!$B$18 -> 0.0063
A8: Output cost | B8: tokens / 1e6 x price | C8: =C6/1000000*Assumptions!$B$19 -> 0.0057
A9: LLM cost per mission | B9: input + output | C9: =C7+C8 -> 0.012
A10: Missions per robot per year | B10: missions/day x operating days | C10: =Assumptions!$B$20*Assumptions!$B$21 -> 880
A11: LLM cost per robot per year | B11: per-mission x missions/yr | C11: =C9*C10 -> 10.56
A13: At roughly one cent per mission the LLM is not a meaningful cost driver. It is included because a business case that shows zero for its central technology invites the question.

Sheet P&L 3 years
A1: Three-year projection
A2: All figures derive from the Assumptions sheet. No hardcoded values below.
A4: Line | B4: Year 1 | C4: Year 2 | D4: Year 3 | E4: Total
A5: Sites (cumulative) | B5: =Assumptions!$B$29 -> 3 | C5: =Assumptions!$B$30 -> 10 | D5: =Assumptions!$B$31 -> 22 | E5: =D5 -> 22
A6: New sites in year | B6: =B5 -> 3 | C6: =C5-B5*(1-Assumptions!$B$33) -> 7.3 | D6: =D5-C5*(1-Assumptions!$B$33) -> 13 | E6: =SUM(B6:D6) -> 23.3
A8: REVENUE
A9: Subscription | B9: =B5*Assumptions!$B$24 -> 28800 | C9: =C5*Assumptions!$B$24 -> 96000 | D9: =D5*Assumptions!$B$24 -> 211200 | E9: =SUM(B9:D9) -> 336000
A10: Hardware resale margin | B10: =B6*Assumptions!$B$32*Assumptions!$B$11*Assumptions!$B$25 -> 9240 | C10: =C6*Assumptions!$B$32*Assumptions!$B$11*Assumptions!$B$25 -> 22484 | D10: =D6*Assumptions!$B$32*Assumptions!$B$11*Assumptions!$B$25 -> 40040 | E10: =SUM(B10:D10) -> 71764
A11: Commissioning fees | B11: =B6*Assumptions!$B$26 -> 7200 | C11: =C6*Assumptions!$B$26 -> 17520 | D11: =D6*Assumptions!$B$26 -> 31200 | E11: =SUM(B11:D11) -> 55920
A12: Total revenue | B12: =SUM(B9:B11) -> 45240 | C12: =SUM(C9:C11) -> 136004 | D12: =SUM(D9:D11) -> 282440 | E12: =SUM(E9:E11) -> 463684
A14: COSTS
A15: Development (year 1 only) | B15: =Assumptions!$B$5*Assumptions!$B$6 -> 31200 | C15: 0 | D15: 0 | E15: =SUM(B15:D15) -> 31200
A16: Software maintenance | B16: 0 | C16: =Assumptions!$B$5*Assumptions!$B$6*Assumptions!$B$8 -> 5616 | D16: =Assumptions!$B$5*Assumptions!$B$6*Assumptions!$B$8 -> 5616 | E16: =SUM(B16:D16) -> 11232
A17: Hardware purchase | B17: =B6*Assumptions!$B$32*Assumptions!$B$11 -> 42000 | C17: =C6*Assumptions!$B$32*Assumptions!$B$11 -> 102200 | D17: =D6*Assumptions!$B$32*Assumptions!$B$11 -> 182000 | E17: =SUM(B17:D17) -> 326200
A18: Hardware maintenance | B18: =B5*Assumptions!$B$32*Assumptions!$B$11*Assumptions!$B$13 -> 4200 | C18: =C5*Assumptions!$B$32*Assumptions!$B$11*Assumptions!$B$13 -> 14000 | D18: =D5*Assumptions!$B$32*Assumptions!$B$11*Assumptions!$B$13 -> 30800 | E18: =SUM(B18:D18) -> 49000
A19: Commissioning delivery | B19: =B6*Assumptions!$B$7*Assumptions!$B$6 -> 4320 | C19: =C6*Assumptions!$B$7*Assumptions!$B$6 -> 10512 | D19: =D6*Assumptions!$B$7*Assumptions!$B$6 -> 18720 | E19: =SUM(B19:D19) -> 33552
A20: LLM consumption | B20: =B5*'Per-mission cost'!$C$11 -> 31.68 | C20: =C5*'Per-mission cost'!$C$11 -> 105.6 | D20: =D5*'Per-mission cost'!$C$11 -> 232.32 | E20: =SUM(B20:D20) -> 369.6
A21: Total costs | B21: =SUM(B15:B20) -> 81751.68 | C21: =SUM(C15:C20) -> 132433.6 | D21: =SUM(D15:D20) -> 237368.32 | E21: =SUM(E15:E20) -> 451553.6
A23: Net result | B23: =B12-B21 -> -36511.68 | C23: =C12-C21 -> 3570.4 | D23: =D12-D21 -> 45071.68 | E23: =E12-E21 -> 12130.4
A24: Cumulative net | B24: =B23 -> -36511.68 | C24: =B24+C23 -> -32941.28 | D24: =C24+D23 -> 12130.4
A26: Break-even | B26: =IF(D24>0,"Within 3 years — cumulative net turns positive","Not within 3 years at these assumptions") -> Within 3 years — cumulative net turns positive
A28: Sensitivity: the three assumptions that move the answer most are subscription price, site count, and hardware cost. Change any of them on the Assumptions sheet and this page recalculates. Development effort and day rate are estimates, not quotations; hardware price should be replaced with a real quotation before this model is used for any decision.
